ivona_speak/__init__.py
ivona_speak/command_line.py
ivona_speak/test/test_command_line.py
ivona_speak-0.3.0.data/scripts/ivona-speak
ivona_speak-0.3.0.dist-info/DESCRIPTION.rst
ivona_speak-0.3.0.dist-info/METADATA
ivona_speak-0.3.0.dist-info/RECORD
ivona_speak-0.3.0.dist-info/WHEEL
ivona_speak-0.3.0.dist-info/metadata.json
ivona_speak-0.3.0.dist-info/top_level.txt
