Metadata-Version: 2.0
Name: ivona-speak
Version: 0.3.0
Summary: Python script that lets you easily convert text to synthesized audio files, with help of Amazon's IVONA.
Home-page: https://github.com/Pythonity/ivona-speak
Author: Paweł Adamczak
Author-email: pawel.adamczak@sidnet.info
License: MIT License
Download-URL: https://github.com/Pythonity/ivona-speak/releases/latest
Keywords: amazon ivona text to speech synthesize
Platform: UNKNOWN
Classifier: Development Status :: 4 - Beta
Classifier: Environment :: Console
Classifier: Intended Audience :: End Users/Desktop
Classifier: License :: OSI Approved :: MIT License
Classifier: Operating System :: OS Independent
Classifier: Programming Language :: Python
Classifier: Programming Language :: Python :: 2
Classifier: Programming Language :: Python :: 2.7
Classifier: Programming Language :: Python :: 3
Classifier: Programming Language :: Python :: 3.4
Classifier: Programming Language :: Python :: 3.5
Classifier: Programming Language :: Python :: 3.6
Classifier: Topic :: Utilities
Requires-Dist: click (>=6.7)
Requires-Dist: click-default-group (>=1.2)
Requires-Dist: ivona-api (>=0.3.0)
Provides-Extra: testing
Requires-Dist: pytest; extra == 'testing'
